bacalhau_sdk/__init__.py
bacalhau_sdk/config.py
bacalhau_sdk/jobs.py
bacalhau_sdk/orchestrator_service.py
bacalhau_sdk-1.4.2.dist-info/METADATA
bacalhau_sdk-1.4.2.dist-info/WHEEL
bacalhau_sdk-1.4.2.dist-info/RECORD
