Metadata-Version: 2.1
Name: bacalhau-sdk
Version: 1.4.2
Summary: Compute over Data framework for public, transparent, and optionally verifiable computation using IPFS & Filecoin.
Home-page: https://github.com/bacalhau-project/bacalhau/
License: Apache-2.0
Keywords: bacalhau,Filecoin,IPFS,cod,compute over data,verifiable computation
Author: Enrico Rotundo
Author-email: team@bacalhau.org
Requires-Python: >=3.8.1,<3.12
Classifier: Development Status :: 2 - Pre-Alpha
Classifier: Intended Audience :: Developers
Classifier: License :: OSI Approved :: Apache Software License
Classifier: Natural Language :: English
Classifier: Programming Language :: Python :: 3
Classifier: Programming Language :: Python :: 3.9
Classifier: Programming Language :: Python :: 3.10
Classifier: Programming Language :: Python :: 3.11
Requires-Dist: bacalhau-apiclient (>=1.0.0)
Requires-Dist: certifi (==2024.2.2)
Requires-Dist: cryptography (>=42.0.0,<43.0.0)
Requires-Dist: mypy (>=1.9)
Requires-Dist: pem (>=23.1.0,<24.0.0)
Requires-Dist: pre-commit (>=2.12.0)
Requires-Dist: pycryptodome (>=3.20.0,<4.0.0)
Requires-Dist: pygments (==2.17.2)
Requires-Dist: ruff (>=0.5.0,<0.6.0)
Requires-Dist: six (>=1.16.0,<2.0.0)
Requires-Dist: toml (>=0.10.2,<0.11.0)
Requires-Dist: tox (>=4.2.6,<5.0.0)
Requires-Dist: twine (>=4.0.2,<5.0.0)
Requires-Dist: types-six (>=1.16.21.4,<2.0.0.0)
Requires-Dist: virtualenv (>=20.2.2,<21.0.0)
Project-URL: Bug Tracker, https://github.com/bacalhau-project/bacalhau/issues
Project-URL: Documentation, https://docs.bacalhau.org/
Project-URL: Repository, https://github.com/bacalhau-project/bacalhau/
